[
    {
        "stepId": "STEP1",
        "stepName": "Url: WebTours",
        "infFile": "t1.inf",
        "time": 1733993979118
    },
    {
        "stepId": "STEP2",
        "stepName": "Submit Data: login.pl",
        "infFile": "t2.inf",
        "time": 1733993982295
    },
    {
        "stepId": "STEP3",
        "stepName": "Url: Search Flights Button",
        "infFile": "t3.inf",
        "time": 1733993987507
    },
    {
        "stepId": "STEP4",
        "stepName": "Submit Data: reservations.pl",
        "infFile": "t4.inf",
        "time": 1733993990645
    },
    {
        "stepId": "STEP5",
        "stepName": "Submit Data: reservations.pl_2",
        "infFile": "t5.inf",
        "time": 1733993995777
    },
    {
        "stepId": "STEP6",
        "stepName": "Submit Data: reservations.pl_3",
        "infFile": "t6.inf",
        "time": 1733994000950
    },
    {
        "stepId": "STEP7",
        "stepName": "Url: welcome.pl_2",
        "infFile": "t7.inf",
        "time": 1733994006109
    }
]